[
  {
    "id": "0",
    "title": "Github Searcher",
    "image": "/proy1.webp",
    "description": "Buscador de usuarios de github, da info,detalles y repos del usuario buscado",
    "skills": ["React", "CSS", "MUI"],
    "websiteLink": "https://github-searcher-2-0.vercel.app/",
    "githubLink": "https://github.com/waldir-xam/github-searcher-2.0"
  },
  {
    "id": "1",
    "title": "Portfolio",
    "image": "proy2.webp",
    "description": "Portfolio con info acerca de mi, proyectos y contacto",
    "skills": ["React", "SCSS"],
    "websiteLink": "https://vercel.com",
    "githubLink": "https://github.com"
  },
  {
    "id": "2",
    "title": "Rick & Morty",
    "image": "proy2.webp",
    "description": "App usando la API fake de Rick & Morty",
    "skills": ["Javascript", "Bootstrap"],
    "websiteLink": "https://rick-y-morty-api-phi.vercel.app/",
    "githubLink": "https://github.com/waldir-xam/Rick-y-Morty-API"
  },
  {
    "id": "3",
    "title": "Task List/To do ",
    "image": "proy3.webp",
    "description": "More projects in progress...",
    "skills": ["React", "Tailwind", "Redux"],
    "websiteLink": "https://react-crud-todo-phi.vercel.app/",
    "githubLink": "https://github.com/waldir-xam/react-crud-todo"
  }
]
